splitty.py
git_barber-0.1.0.dist-info/LICENSE
git_barber-0.1.0.dist-info/METADATA
git_barber-0.1.0.dist-info/WHEEL
git_barber-0.1.0.dist-info/entry_points.txt
git_barber-0.1.0.dist-info/top_level.txt
git_barber-0.1.0.dist-info/RECORD
