Metadata-Version: 2.1
Name: git-barber
Version: 0.1.0
Summary: UNKNOWN
Home-page: UNKNOWN
License: UNKNOWN
Platform: UNKNOWN
License-File: LICENSE
Requires-Dist: click
Requires-Dist: GitPython
Requires-Dist: inquirer
